window_functions/__init__.py
window_functions/main.py
window_functions-0.1.dist-info/METADATA
window_functions-0.1.dist-info/WHEEL
window_functions-0.1.dist-info/top_level.txt
window_functions-0.1.dist-info/RECORD
